LICENSE.rst
README.md
setup.cfg
setup.py
depronounize/__init__.py
depronounize/depronounize.py
depronounize/female_names.py
depronounize/female_nouns.py
depronounize/feminine.py
depronounize/male_names.py
depronounize/male_nouns.py
depronounize/masculine.py
depronounize/pronouns_gender_number.py
depronounize.egg-info/PKG-INFO
depronounize.egg-info/SOURCES.txt
depronounize.egg-info/dependency_links.txt
depronounize.egg-info/not-zip-safe
depronounize.egg-info/requires.txt
depronounize.egg-info/top_level.txt
tests/__init__.py
tests/test.py