Metadata-Version: 1.0
Name: depronounize
Version: 1.0.11
Summary: Pronoun replacement module
Home-page: https://github.com/NazarTrilisky/PronounReplacement
Author: Nazar Trilisky
Author-email: UNKNOWN
License: MIT
Platform: UNKNOWN
